{"cameraMode":{"drawMode":0,"name":"Shaded","section":"Shading Mode"},"sceneLighting":true,"audioPlay":false,"sceneViewState":{"showFog":true,"showMaterialUpdate":false,"showSkybox":true,"showFlares":true,"showImageEffects":true,"showParticleSystems":true},"in2DMode":false,"pivot":{"x":-21.51370620727539,"y":-9.099052429199219,"z":22.006370544433595},"rotation":{"x":-0.16572804749011994,"y":0.3864841163158417,"z":-0.07080735266208649,"w":-0.9045250415802002},"size":24.734861373901368,"orthographic":false}